pyjinhx/__init__.py
pyjinhx/base.py
pyjinhx/dataclasses.py
pyjinhx/finder.py
pyjinhx/parser.py
pyjinhx/registry.py
pyjinhx/renderer.py
pyjinhx/utils.py
pyjinhx-0.2.8.dist-info/METADATA
pyjinhx-0.2.8.dist-info/WHEEL
pyjinhx-0.2.8.dist-info/licenses/LICENSE.txt
pyjinhx-0.2.8.dist-info/RECORD
