Metadata-Version: 2.4
Name: pyjinhx
Version: 0.2.8
Summary: UI components for Python using Pydantic and Jinja2 templates
Project-URL: Homepage, https://github.com/paulomtts/pyjinhx
Author-email: Paulo Mattos <paulomtts@outlook.com>
License: MIT
License-File: LICENSE.txt
Keywords: ,components,jinja2,pydantic,templates,ui
Classifier: Development Status :: 3 - Alpha
Classifier: Intended Audience :: Developers
Classifier: License :: OSI Approved :: MIT License
Classifier: Programming Language :: Python :: 3
Classifier: Programming Language :: Python :: 3.13
Requires-Python: >=3.13
Requires-Dist: jinja2>=3.1.6
Requires-Dist: markupsafe>=3.0.3
Requires-Dist: pydantic>=2.12.5
Requires-Dist: pytest>=9.0.1
